src/dooray-mcp-server.py
mseep_dooray_mcp-0.1.1.dist-info/METADATA
mseep_dooray_mcp-0.1.1.dist-info/WHEEL
mseep_dooray_mcp-0.1.1.dist-info/licenses/LICENSE
mseep_dooray_mcp-0.1.1.dist-info/RECORD
